main/__init__.py
main/lijiaheng.py
lijiaheng-3.0.dist-info/METADATA
lijiaheng-3.0.dist-info/WHEEL
lijiaheng-3.0.dist-info/entry_points.txt
lijiaheng-3.0.dist-info/top_level.txt
lijiaheng-3.0.dist-info/RECORD
